aao/api/__init__.py
aao/api/api.py
aao/spiders/__init__.py
aao/spiders/spider.py
aao/spiders/spider_888sport.py
aao/spiders/spider_bet365.py
aao/spiders/spider_bwin.py
aao/spiders/spider_williamhill.py
aao-0.0.1.dist-info/DESCRIPTION.rst
aao-0.0.1.dist-info/METADATA
aao-0.0.1.dist-info/RECORD
aao-0.0.1.dist-info/WHEEL
aao-0.0.1.dist-info/metadata.json
aao-0.0.1.dist-info/top_level.txt
