Metadata-Version: 2.0
Name: aao
Version: 0.0.1
Summary: An environment where you can test your betting strategies
Home-page: https://github.com/S1M0N38/aao
Author: S1M0N38
Author-email: bertolottosimone@gmail.com
License: MIT
Platform: UNKNOWN
Classifier: Development Status :: 1 - Planning
Classifier: License :: OSI Approved :: MIT License
Classifier: Programming Language :: Python :: 3.6
Classifier: Programming Language :: Python :: 3.7
Requires-Python: >=3.6.0
Requires-Dist: selenium
